telegramtk/__init__.py
telegramtk/core.py
telegramtk/exceptions.py
telegramtk/settings.py
telegramtk/utils.py
telegramtk-0.1.0.dist-info/LICENSE
telegramtk-0.1.0.dist-info/METADATA
telegramtk-0.1.0.dist-info/WHEEL
telegramtk-0.1.0.dist-info/top_level.txt
telegramtk-0.1.0.dist-info/RECORD
