Metadata-Version: 2.1
Name: telegramtk
Version: 0.1.0
Summary: Telegram toolkit
Home-page: https://github.com/sdelquin/telegramtk.git
Author: Sergio Delgado Quintero
Author-email: sdelquin@gmail.com
License: MIT
License-File: LICENSE
Requires-Dist: requests
